{"id":"5da92c3c7ce68","start_date":{"date":"2019-10-18 05:06:36.513201","timezone_type":3,"timezone":"Europe\/Paris"},"end_date":{"date":"2019-10-18 05:07:05.289222","timezone_type":3,"timezone":"Europe\/Paris"},"duration":null,"commits":[{"id":"5da92c4107d66","create_date":{"date":"2019-10-18 05:06:41.033756","timezone_type":3,"timezone":"Europe\/Paris"},"message":"Test Commit when tracking 1.","step":{"start_date":{"date":"2019-10-18 05:06:36.513201","timezone_type":3,"timezone":"Europe\/Paris"},"end_date":{"date":"2019-10-18 05:06:41.033794","timezone_type":3,"timezone":"Europe\/Paris"},"duration":"00:00:04","commit":"5da92c4107d66"}},{"id":"5da92c4b0c47d","create_date":{"date":"2019-10-18 05:06:51.051930","timezone_type":3,"timezone":"Europe\/Paris"},"message":"Test Commit when tracking 2.","step":{"start_date":{"date":"2019-10-18 05:06:41.033862","timezone_type":3,"timezone":"Europe\/Paris"},"end_date":{"date":"2019-10-18 05:06:51.051968","timezone_type":3,"timezone":"Europe\/Paris"},"duration":"00:00:10","commit":"5da92c4b0c47d"}},{"id":"5da92d42c5c84","create_date":{"date":"2019-10-18 05:10:58.811726","timezone_type":3,"timezone":"Europe\/Paris"},"message":"Test Commit when tracking 3.","step":{"start_date":{"date":"2019-10-18 05:10:09.329587","timezone_type":3,"timezone":"Europe\/Paris"},"end_date":{"date":"2019-10-18 05:10:52.584875","timezone_type":3,"timezone":"Europe\/Paris"},"duration":"00:00:43","commit":"5da92d42c5c84"}},{"id":"5da92e285029f","create_date":{"date":"2019-10-18 05:14:48.329986","timezone_type":3,"timezone":"Europe\/Paris"},"message":"Test Commit when tracking 4.","step":{"start_date":{"date":"2019-10-18 05:14:12.474253","timezone_type":3,"timezone":"Europe\/Paris"},"end_date":{"date":"2019-10-18 05:14:42.528171","timezone_type":3,"timezone":"Europe\/Paris"},"duration":"00:00:30","commit":"5da92e285029f"}}],"steps":[{"start_date":{"date":"2019-10-18 05:06:36.513201","timezone_type":3,"timezone":"Europe\/Paris"},"end_date":{"date":"2019-10-18 05:06:41.033794","timezone_type":3,"timezone":"Europe\/Paris"},"duration":"00:00:04","commit":"5da92c4107d66"},{"start_date":{"date":"2019-10-18 05:06:41.033862","timezone_type":3,"timezone":"Europe\/Paris"},"end_date":{"date":"2019-10-18 05:06:51.051968","timezone_type":3,"timezone":"Europe\/Paris"},"duration":"00:00:10","commit":"5da92c4b0c47d"},{"start_date":{"date":"2019-10-18 05:06:51.052037","timezone_type":3,"timezone":"Europe\/Paris"},"end_date":{"date":"2019-10-18 05:07:05.289258","timezone_type":3,"timezone":"Europe\/Paris"},"duration":"00:00:14"},{"start_date":{"date":"2019-10-18 05:07:09.682324","timezone_type":3,"timezone":"Europe\/Paris"},"end_date":{"date":"2019-10-18 05:09:51.209670","timezone_type":3,"timezone":"Europe\/Paris"},"duration":"00:02:41"},{"start_date":{"date":"2019-10-18 05:09:53.114000","timezone_type":3,"timezone":"Europe\/Paris"},"end_date":{"date":"2019-10-18 05:10:02.120901","timezone_type":3,"timezone":"Europe\/Paris"},"duration":"00:00:09"},{"start_date":{"date":"2019-10-18 05:10:09.329587","timezone_type":3,"timezone":"Europe\/Paris"},"end_date":{"date":"2019-10-18 05:10:52.584875","timezone_type":3,"timezone":"Europe\/Paris"},"duration":"00:00:43","commit":"5da92d42c5c84"},{"start_date":{"date":"2019-10-18 05:10:58.811784","timezone_type":3,"timezone":"Europe\/Paris"},"end_date":{"date":"2019-10-18 05:11:25.024866","timezone_type":3,"timezone":"Europe\/Paris"},"duration":"00:00:26"},{"start_date":{"date":"2019-10-18 05:13:36.072948","timezone_type":3,"timezone":"Europe\/Paris"},"end_date":{"date":"2019-10-18 05:14:03.352870","timezone_type":3,"timezone":"Europe\/Paris"},"duration":"00:00:27"},{"start_date":{"date":"2019-10-18 05:14:06.361553","timezone_type":3,"timezone":"Europe\/Paris"},"end_date":{"date":"2019-10-18 05:14:10.264913","timezone_type":3,"timezone":"Europe\/Paris"},"duration":"00:00:03"},{"start_date":{"date":"2019-10-18 05:14:12.474253","timezone_type":3,"timezone":"Europe\/Paris"},"end_date":{"date":"2019-10-18 05:14:42.528171","timezone_type":3,"timezone":"Europe\/Paris"},"duration":"00:00:30","commit":"5da92e285029f"},{"start_date":{"date":"2019-10-18 05:14:48.330040","timezone_type":3,"timezone":"Europe\/Paris"},"end_date":{"date":"2019-10-18 05:16:28.465679","timezone_type":3,"timezone":"Europe\/Paris"},"duration":"00:01:40"}],"run":false,"report":{"file":".\/reports\/report-5da92c3c7ce68.json"}}