{"id":"5da92f45e0f72","start_date":{"date":"2019-10-18 05:19:33.923069","timezone_type":3,"timezone":"Europe\/Paris"},"end_date":{"date":"2019-10-18 05:19:46.944659","timezone_type":3,"timezone":"Europe\/Paris"},"duration":null,"commits":[{"id":"5da92f4864e0f","create_date":{"date":"2019-10-18 05:19:36.415020","timezone_type":3,"timezone":"Europe\/Paris"},"message":"Test Commit when tracking 1.","step":{"start_date":{"date":"2019-10-18 05:19:33.923069","timezone_type":3,"timezone":"Europe\/Paris"},"end_date":{"date":"2019-10-18 05:19:36.415063","timezone_type":3,"timezone":"Europe\/Paris"},"duration":"00:00:02","commit":"5da92f4864e0f"}},{"id":"5da92f4c1d04e","create_date":{"date":"2019-10-18 05:19:40.120460","timezone_type":3,"timezone":"Europe\/Paris"},"message":"Test Commit when tracking 2.","step":{"start_date":{"date":"2019-10-18 05:19:36.415141","timezone_type":3,"timezone":"Europe\/Paris"},"end_date":{"date":"2019-10-18 05:19:40.120497","timezone_type":3,"timezone":"Europe\/Paris"},"duration":"00:00:03","commit":"5da92f4c1d04e"}}],"steps":[{"start_date":{"date":"2019-10-18 05:19:33.923069","timezone_type":3,"timezone":"Europe\/Paris"},"end_date":{"date":"2019-10-18 05:19:36.415063","timezone_type":3,"timezone":"Europe\/Paris"},"duration":"00:00:02","commit":"5da92f4864e0f"},{"start_date":{"date":"2019-10-18 05:19:36.415141","timezone_type":3,"timezone":"Europe\/Paris"},"end_date":{"date":"2019-10-18 05:19:40.120497","timezone_type":3,"timezone":"Europe\/Paris"},"duration":"00:00:03","commit":"5da92f4c1d04e"},{"start_date":{"date":"2019-10-18 05:19:40.120566","timezone_type":3,"timezone":"Europe\/Paris"},"end_date":{"date":"2019-10-18 05:19:46.944695","timezone_type":3,"timezone":"Europe\/Paris"},"duration":"00:00:06"}],"run":false,"report":{"file":".\/reports\/report-5da92f45e0f72.json"}}